{
  "updated": "2026-04-28T18:48:13.657Z",
  "summary": {
    "label": "sk-or-v1-e99...dcc",
    "is_management_key": false,
    "is_provisioning_key": false,
    "limit": null,
    "limit_reset": null,
    "limit_remaining": null,
    "include_byok_in_limit": false,
    "usage": 314.50272445,
    "usage_daily": 42.8187651,
    "usage_weekly": 174.11988605,
    "usage_monthly": 314.50272445,
    "byok_usage": 0,
    "byok_usage_daily": 0,
    "byok_usage_weekly": 0,
    "byok_usage_monthly": 0,
    "is_free_tier": false,
    "expires_at": null,
    "creator_user_id": "user_3Cl5BcSNEfr1V41P80AtsbW89WR",
    "rate_limit": {
      "requests": -1,
      "interval": "10s",
      "note": "This field is deprecated and safe to ignore."
    }
  },
  "daily_breakdown": {}
}